unicorefw/__init__.py
unicorefw/array.py
unicorefw/core.py
unicorefw/crypto.py
unicorefw/db.py
unicorefw/function.py
unicorefw/object.py
unicorefw/security.py
unicorefw/string.py
unicorefw/supporter.py
unicorefw/template.py
unicorefw/types.py
unicorefw/utils.py
unicorefw-1.1.2.dist-info/LICENSE
unicorefw-1.1.2.dist-info/METADATA
unicorefw-1.1.2.dist-info/WHEEL
unicorefw-1.1.2.dist-info/top_level.txt
unicorefw-1.1.2.dist-info/RECORD
