Metadata-Version: 2.1
Name: unicorefw
Version: 1.1.2
Summary: Universal Core Utility Library
Home-page: https://github.com/unicorefw-org/unicorefw-py
Author: Kenny Ngo
Author-email: kenny@unicorefw.org
License: UNKNOWN
Project-URL: Bug Tracker, https://github.com/unicorefw-org/unicorefw-py/issues
Project-URL: Documentation, https://unicorefw.org
Platform: UNKNOWN
Classifier: Programming Language :: Python :: 3
Classifier: Programming Language :: Python :: 3.7
Classifier: Programming Language :: Python :: 3.8
Classifier: Programming Language :: Python :: 3.9
Classifier: Programming Language :: Python :: 3.10
Classifier: License :: OSI Approved :: BSD License
Classifier: Operating System :: OS Independent
Classifier: Intended Audience :: Developers
Classifier: Topic :: Software Development :: Libraries :: Python Modules
Requires-Python: >=3.7
